pival/__init__.py
pival-1.1.1.dist-info/LICENSE
pival-1.1.1.dist-info/METADATA
pival-1.1.1.dist-info/WHEEL
pival-1.1.1.dist-info/top_level.txt
pival-1.1.1.dist-info/RECORD
