Metadata-Version: 2.1
Name: pival
Version: 1.1.1
Summary: python module for pi's value!
Home-page: https://github.com/Whirlpool-Programmer/pival
Author: Whirlpool-Programmer
Author-email: whirlpool.programmer@outlook.com
License: MIT License
Platform: UNKNOWN
Classifier: Programming Language :: Python :: 2
Classifier: Programming Language :: Python :: 3
Classifier: License :: OSI Approved :: MIT License
Classifier: Operating System :: OS Independent
